Bambanta/AutoDiff.py
Bambanta/__init__.py
Bambanta/test_AutoDiff.py
Bambanta-0.1.4.dist-info/LICENSE
Bambanta-0.1.4.dist-info/METADATA
Bambanta-0.1.4.dist-info/WHEEL
Bambanta-0.1.4.dist-info/top_level.txt
Bambanta-0.1.4.dist-info/RECORD
