Metadata-Version: 2.1
Name: Bambanta
Version: 0.1.4
Summary: An automatic differentiation package
Home-page: https://github.com/CS207-Project-Group-9/cs207-FinalProject
Author: Karina Huang, Rong Liu, Rory Maizels
License: MIT
Platform: UNKNOWN
Classifier: Development Status :: 5 - Production/Stable
Classifier: Programming Language :: Python :: 3
Classifier: License :: OSI Approved :: MIT License
Classifier: Operating System :: OS Independent
Requires-Dist: numpy
